odoo/addons/base_rest_auth_api_key/README.rst
odoo/addons/base_rest_auth_api_key/__init__.py
odoo/addons/base_rest_auth_api_key/__manifest__.py
odoo/addons/base_rest_auth_api_key/apispec/__init__.py
odoo/addons/base_rest_auth_api_key/apispec/rest_method_security_plugin.py
odoo/addons/base_rest_auth_api_key/components/__init__.py
odoo/addons/base_rest_auth_api_key/components/service.py
odoo/addons/base_rest_auth_api_key/i18n/base_rest_auth_api_key.pot
odoo/addons/base_rest_auth_api_key/i18n/it.po
odoo/addons/base_rest_auth_api_key/i18n/sv.po
odoo/addons/base_rest_auth_api_key/readme/CONTRIBUTORS.md
odoo/addons/base_rest_auth_api_key/readme/DESCRIPTION.md
odoo/addons/base_rest_auth_api_key/static/description/icon.png
odoo/addons/base_rest_auth_api_key/static/description/index.html
odoo_addon_base_rest_auth_api_key-18.0.1.1.0.3.dist-info/METADATA
odoo_addon_base_rest_auth_api_key-18.0.1.1.0.3.dist-info/WHEEL
odoo_addon_base_rest_auth_api_key-18.0.1.1.0.3.dist-info/top_level.txt
odoo_addon_base_rest_auth_api_key-18.0.1.1.0.3.dist-info/RECORD
