Metadata-Version: 2.1
Name: odoo-addon-base_rest_auth_api_key
Version: 18.0.1.1.0.3
Requires-Python: >=3.10
Requires-Dist: apispec
Requires-Dist: odoo-addon-auth_api_key==18.0.*
Requires-Dist: odoo-addon-base_rest==18.0.*
Requires-Dist: odoo==18.0.*
Summary: Base Rest: Add support for the auth_api_key security policy into the openapi documentation
Home-page: https://github.com/OCA/rest-framework
License: LGPL-3
Author: ACSONE SA/NV,Odoo Community Association (OCA)
Author-email: support@odoo-community.org
Classifier: Programming Language :: Python
Classifier: Framework :: Odoo
Classifier: Framework :: Odoo :: 18.0
Classifier: License :: OSI Approved :: GNU Lesser General Public License v3 (LGPLv3)
